MANIFEST.in
Makefile
PKGBUILD
README.rest
revers.py
reverstorm.py
setup.py
revers.py.egg-info/PKG-INFO
revers.py.egg-info/SOURCES.txt
revers.py.egg-info/dependency_links.txt
revers.py.egg-info/requires.txt
revers.py.egg-info/top_level.txt
revers.py.egg-info/zip-safe