Metadata-Version: 1.0
Name: revers.py
Version: 0.2
Summary: Reverse Entity-Relationship Storm
Home-page: http://pypi.python.org/pypi/revers
Author: Vsevolod Balashov
Author-email: vsevolod@balashov.name
License: GPL 3
Keywords: python storm reverse
Platform: UNKNOWN
Classifier: Development Status :: 3 - Alpha
Classifier: Environment :: Console
Classifier: Intended Audience :: Developers
Classifier: License :: OSI Approved :: GNU General Public License (GPL)
Classifier: Natural Language :: Russian
Classifier: Operating System :: OS Independent
Classifier: Programming Language :: Python
Classifier: Topic :: Database
